pystarburst/__init__.py
pystarburst/_internal/__init__.py
pystarburst/_internal/analyzer/__init__.py
pystarburst/_internal/analyzer/analyzer.py
pystarburst/_internal/analyzer/analyzer_utils.py
pystarburst/_internal/analyzer/base_model.py
pystarburst/_internal/analyzer/dataframe_api_client.py
pystarburst/_internal/analyzer/expression/__init__.py
pystarburst/_internal/analyzer/expression/binary.py
pystarburst/_internal/analyzer/expression/general.py
pystarburst/_internal/analyzer/expression/grouping_set.py
pystarburst/_internal/analyzer/expression/sort.py
pystarburst/_internal/analyzer/expression/table.py
pystarburst/_internal/analyzer/expression/table_function.py
pystarburst/_internal/analyzer/expression/unary.py
pystarburst/_internal/analyzer/expression/window.py
pystarburst/_internal/analyzer/plan/__init__.py
pystarburst/_internal/analyzer/plan/logical_plan/__init__.py
pystarburst/_internal/analyzer/plan/logical_plan/binary.py
pystarburst/_internal/analyzer/plan/logical_plan/leaf.py
pystarburst/_internal/analyzer/plan/logical_plan/table.py
pystarburst/_internal/analyzer/plan/logical_plan/table_function.py
pystarburst/_internal/analyzer/plan/logical_plan/unary.py
pystarburst/_internal/analyzer/plan/trino_plan.py
pystarburst/_internal/error_message.py
pystarburst/_internal/server_connection.py
pystarburst/_internal/type_utils.py
pystarburst/_internal/utils.py
pystarburst/column.py
pystarburst/context.py
pystarburst/dataframe.py
pystarburst/dataframe_na_functions.py
pystarburst/dataframe_stat_functions.py
pystarburst/dataframe_writer.py
pystarburst/exceptions.py
pystarburst/functions.py
pystarburst/query_history.py
pystarburst/relational_grouped_dataframe.py
pystarburst/result_cache.py
pystarburst/row.py
pystarburst/session.py
pystarburst/table.py
pystarburst/table_function.py
pystarburst/types.py
pystarburst/window.py
pystarburst-0.10.0.dist-info/LICENSE.txt
pystarburst-0.10.0.dist-info/METADATA
pystarburst-0.10.0.dist-info/WHEEL
pystarburst-0.10.0.dist-info/RECORD
