Metadata-Version: 2.3
Name: pystarburst
Version: 0.10.0
Summary: PyStarburst DataFrame API allows you to query and transform data in Starburst products in a data pipeline without having to download the data locally.
License: Apache-2.0
Author: Starburst Data
Author-email: info@starburstdata.com
Requires-Python: >=3.9,<4.0
Classifier: License :: OSI Approved :: Apache Software License
Classifier: Programming Language :: Python :: 3
Classifier: Programming Language :: Python :: 3.9
Classifier: Programming Language :: Python :: 3.10
Classifier: Programming Language :: Python :: 3.11
Classifier: Programming Language :: Python :: 3.12
Classifier: Programming Language :: Python :: 3.13
Provides-Extra: pandas
Requires-Dist: pandas (>=2.2,<3.0) ; extra == "pandas"
Requires-Dist: pydantic (>=2.7.4,<3.0.0)
Requires-Dist: python-dateutil (>=2.8.2,<3.0.0)
Requires-Dist: trino (>=0.335.0,<0.336.0)
Requires-Dist: urllib3 (>=2.5.0,<3.0.0)
Requires-Dist: zstandard (>=0.23.0,<0.24.0)
Project-URL: Homepage, https://starburst.io
Project-URL: Repository, https://github.com/starburstdata/pystarburst-examples
